input
lib1
output
